english_detector/__init__.py
english_detector/main.py
english_detector-0.1.0.dist-info/LICENSE
english_detector-0.1.0.dist-info/METADATA
english_detector-0.1.0.dist-info/WHEEL
english_detector-0.1.0.dist-info/top_level.txt
english_detector-0.1.0.dist-info/RECORD
