Metadata-Version: 2.1
Name: english-detector
Version: 0.1.0
Summary: A python package to detect english text
Home-page: https://github.com/apinanyogaratnam/english-detector
Author: apinanyogaratnam
Author-email: apinanapinan@icloud.com
Classifier: Programming Language :: Python :: 3
Classifier: License :: OSI Approved :: MIT License
Classifier: Operating System :: OS Independent
Requires-Python: >=3.10.4
License-File: LICENSE
Requires-Dist: pycld2 (==0.41)
